promtsmithsdk/__init__.py
promtsmithsdk/interfaces.py
promtsmithsdk/prompt_smith.py
promtsmithsdk-0.2.1.dist-info/LICENSE
promtsmithsdk-0.2.1.dist-info/METADATA
promtsmithsdk-0.2.1.dist-info/WHEEL
promtsmithsdk-0.2.1.dist-info/RECORD
